df_permission/__init__.py
df_permission/admin.py
df_permission/apps.py
df_permission/models.py
df_permission/permissions.py
df_permission/tests.py
df_permission/variables.py
df_permission/views.py
df_permission/management/__init__.py
df_permission/management/commands/__init__.py
df_permission/management/commands/generate_model_field_permissions.py
df_permission/management/commands/generate_serializer_field_permissions.py
df_permission-0.1.9.dist-info/METADATA
df_permission-0.1.9.dist-info/WHEEL
df_permission-0.1.9.dist-info/top_level.txt
df_permission-0.1.9.dist-info/RECORD
