Metadata-Version: 2.1
Name: df-permission
Version: 0.1.9
Summary: Django field permission package
Author: Maxmudov Asliddin
Author-email: <asliddin750750@gmail.com>
Keywords: python,field,permission,field permission,django field
Classifier: Development Status :: 1 - Planning
Classifier: Intended Audience :: Developers
Classifier: Programming Language :: Python :: 3
Classifier: Operating System :: Unix
Classifier: Operating System :: MacOS :: MacOS X
Classifier: Operating System :: Microsoft :: Windows
Requires-Dist: Django
Requires-Dist: djangorestframework
